jsa_queryservice/__init__.py
jsa_queryservice/apps.py
jsa_queryservice/functions.py
jsa_queryservice/urls.py
jsa_queryservice/views.py
jsa_queryservice-0.0.1.1.dist-info/LICENSE
jsa_queryservice-0.0.1.1.dist-info/METADATA
jsa_queryservice-0.0.1.1.dist-info/WHEEL
jsa_queryservice-0.0.1.1.dist-info/top_level.txt
jsa_queryservice-0.0.1.1.dist-info/RECORD
